README.txt
bootstrap.py
buildout.cfg
setup.py
versions.cfg
collective/__init__.py
collective.piwik.pageviews.egg-info/PKG-INFO
collective.piwik.pageviews.egg-info/SOURCES.txt
collective.piwik.pageviews.egg-info/dependency_links.txt
collective.piwik.pageviews.egg-info/entry_points.txt
collective.piwik.pageviews.egg-info/namespace_packages.txt
collective.piwik.pageviews.egg-info/not-zip-safe
collective.piwik.pageviews.egg-info/requires.txt
collective.piwik.pageviews.egg-info/top_level.txt
collective/piwik/__init__.py
collective/piwik/pageviews/__init__.py
collective/piwik/pageviews/configure.zcml
collective/piwik/pageviews/tests.py
collective/piwik/pageviews/version.txt
collective/piwik/pageviews/view.py
collective/piwik/pageviews/viewlet.pt
collective/piwik/pageviews/viewlets.py
docs/CONTRIBUTORS.txt
docs/HISTORY.txt
docs/INSTALL.txt
docs/LICENSE.GPL
docs/LICENSE.txt