Metadata-Version: 1.0
Name: collective.piwik.pageviews
Version: 0.2
Summary: Analytics support for pages using Piwik
Home-page: http://svn.plone.org/svn/collective/collective.piwik.pageviews
Author: unweb.me
Author-email: we@unweb.me
License: GPL
Keywords: pageviews analytics piwik
Platform: UNKNOWN
Classifier: Framework :: Plone
Classifier: Programming Language :: Python
